niceposter/__init__.py
niceposter/Create.py
niceposter-0.1.5.dist-info/WHEEL
niceposter-0.1.5.dist-info/METADATA
niceposter-0.1.5.dist-info/RECORD
