Metadata-Version: 2.1
Name: niceposter
Version: 0.1.5
Summary: Image Manipulation Tool - Used for creating & modifying image posters
Home-page: https://github.com/amajai/niceposter
License: GPL-3.0-or-later
Keywords: pillow,poster,image-processing,editor
Author: A.A.Isa
Author-email: aabdulmajeed.isa@gmail.com
Requires-Python: >=3.8,<4.0
Classifier: License :: OSI Approved :: GNU General Public License v3 or later (GPLv3+)
Classifier: Programming Language :: Python :: 3
Classifier: Programming Language :: Python :: 3.8
Classifier: Programming Language :: Python :: 3.9
Requires-Dist: Pillow (>=8.0.1,<9.0.0)
